lazy_testdata/__init__.py
lazy_testdata/chinacitycode.py
lazy_testdata/chinesecardbin.py
lazy_testdata/chinesename.py
lazy_testdata/core.py
lazy_testdata/dbhelper.py
lazy_testdata/pthelper.py
lazy_testdata/sh_and_os_ext.py
lazy_testdata-1.1.35.dist-info/METADATA
lazy_testdata-1.1.35.dist-info/WHEEL
lazy_testdata-1.1.35.dist-info/top_level.txt
lazy_testdata-1.1.35.dist-info/RECORD
