Metadata-Version: 2.4
Name: lazy_testdata
Version: 1.1.35
Summary: testdata include chinese personal four element and offen use datetime 测试数据包含随机生成的中国公民四要素，及常用的日期时间 根据swagger文档生成规则用例 用于性能测试摸高，并生成统一测试报告
Home-page: https://www.cnblogs.com/yicaifeitian
Author: YuWeiPeng
Author-email: 404051211@qq.com
Classifier: Programming Language :: Python :: 3
Classifier: License :: OSI Approved :: MIT License
Classifier: Operating System :: OS Independent
Requires-Python: >=3.6
Requires-Dist: json2html>=1.3.0
Requires-Dist: pandas>=2.3.1
Requires-Dist: python-dateutil>=2.9.0
Requires-Dist: records>=0.6.0
Requires-Dist: requests>=2.32.4
Requires-Dist: setuptools>=80.9.0
Requires-Dist: SQLAlchemy>=2.0.41
Requires-Dist: dotenv>=0.9.9
Requires-Dist: python-dotenv>=1.1.1
Dynamic: author
Dynamic: author-email
Dynamic: classifier
Dynamic: description
Dynamic: description-content-type
Dynamic: home-page
Dynamic: requires-dist
Dynamic: requires-python
Dynamic: summary
